<annotation><folder>crop/images/</folder><filename>0235db857_4.jpg</filename><size><width>668</width><height>471</height><depth>3</depth></size><segmented>0</segmented><object><name>ship</name><pose>Unspecified</pose><truncated>0</truncated><difficult>0</difficult><bndbox><xmin>75</xmin><ymin>373</ymin><xmax>239</xmax><ymax>401</ymax></bndbox></object><object><name>ship</name><pose>Unspecified</pose><truncated>0</truncated><difficult>0</difficult><bndbox><xmin>91</xmin><ymin>52</ymin><xmax>314</xmax><ymax>86</ymax></bndbox></object><object><name>ship</name><pose>Unspecified</pose><truncated>0</truncated><difficult>0</difficult><bndbox><xmin>125</xmin><ymin>8</ymin><xmax>298</xmax><ymax>34</ymax></bndbox></object><object><name>ship</name><pose>Unspecified</pose><truncated>0</truncated><difficult>0</difficult><bndbox><xmin>65</xmin><ymin>250</ymin><xmax>229</xmax><ymax>279</ymax></bndbox></object><object><name>ship</name><pose>Unspecified</pose><truncated>0</truncated><difficult>0</difficult><bndbox><xmin>304</xmin><ymin>241</ymin><xmax>472</xmax><ymax>264</ymax></bndbox></object><object><name>ship</name><pose>Unspecified</pose><truncated>0</truncated><difficult>0</difficult><bndbox><xmin>347</xmin><ymin>1</ymin><xmax>515</xmax><ymax>23</ymax></bndbox></object></annotation>