<annotation><folder>crop/images/</folder><filename>2d1c39aef_14.jpg</filename><size><width>474</width><height>218</height><depth>3</depth></size><segmented>0</segmented><object><name>ship</name><pose>Unspecified</pose><truncated>0</truncated><difficult>0</difficult><bndbox><xmin>429</xmin><ymin>157</ymin><xmax>470</xmax><ymax>180</ymax></bndbox></object><object><name>ship</name><pose>Unspecified</pose><truncated>0</truncated><difficult>0</difficult><bndbox><xmin>361</xmin><ymin>161</ymin><xmax>389</xmax><ymax>177</ymax></bndbox></object></annotation>