<annotation><folder>crop/images/</folder><filename>8a40d04f0_29.jpg</filename><size><width>767</width><height>768</height><depth>3</depth></size><segmented>0</segmented><object><name>ship</name><pose>Unspecified</pose><truncated>0</truncated><difficult>0</difficult><bndbox><xmin>401</xmin><ymin>73</ymin><xmax>409</xmax><ymax>83</ymax></bndbox></object><object><name>ship</name><pose>Unspecified</pose><truncated>0</truncated><difficult>0</difficult><bndbox><xmin>603</xmin><ymin>324</ymin><xmax>617</xmax><ymax>332</ymax></bndbox></object><object><name>ship</name><pose>Unspecified</pose><truncated>0</truncated><difficult>0</difficult><bndbox><xmin>300</xmin><ymin>52</ymin><xmax>310</xmax><ymax>62</ymax></bndbox></object></annotation>