<annotation><folder>crop/images/</folder><filename>a0e46d4bc_2.jpg</filename><size><width>63</width><height>42</height><depth>3</depth></size><segmented>0</segmented><object><name>ship</name><pose>Unspecified</pose><truncated>0</truncated><difficult>0</difficult><bndbox><xmin>10</xmin><ymin>6</ymin><xmax>56</xmax><ymax>30</ymax></bndbox></object><object><name>ship</name><pose>Unspecified</pose><truncated>0</truncated><difficult>0</difficult><bndbox><xmin>6</xmin><ymin>1</ymin><xmax>52</xmax><ymax>25</ymax></bndbox></object><object><name>ship</name><pose>Unspecified</pose><truncated>0</truncated><difficult>0</difficult><bndbox><xmin>13</xmin><ymin>14</ymin><xmax>58</xmax><ymax>38</ymax></bndbox></object></annotation>