<annotation><folder>crop/images/</folder><filename>b5c304f8c_29.jpg</filename><size><width>768</width><height>768</height><depth>3</depth></size><segmented>0</segmented><object><name>ship</name><pose>Unspecified</pose><truncated>0</truncated><difficult>0</difficult><bndbox><xmin>347</xmin><ymin>737</ymin><xmax>421</xmax><ymax>767</ymax></bndbox></object><object><name>ship</name><pose>Unspecified</pose><truncated>0</truncated><difficult>0</difficult><bndbox><xmin>293</xmin><ymin>231</ymin><xmax>365</xmax><ymax>297</ymax></bndbox></object></annotation>