<annotation><folder>crop/images/</folder><filename>b85704d01_29.jpg</filename><size><width>768</width><height>530</height><depth>3</depth></size><segmented>0</segmented><object><name>ship</name><pose>Unspecified</pose><truncated>0</truncated><difficult>0</difficult><bndbox><xmin>165</xmin><ymin>470</ymin><xmax>177</xmax><ymax>481</ymax></bndbox></object><object><name>ship</name><pose>Unspecified</pose><truncated>0</truncated><difficult>0</difficult><bndbox><xmin>267</xmin><ymin>441</ymin><xmax>283</xmax><ymax>455</ymax></bndbox></object></annotation>