<annotation><folder>crop/images/</folder><filename>f88d8b6a4_29.jpg</filename><size><width>768</width><height>666</height><depth>3</depth></size><segmented>0</segmented><object><name>ship</name><pose>Unspecified</pose><truncated>0</truncated><difficult>0</difficult><bndbox><xmin>401</xmin><ymin>583</ymin><xmax>423</xmax><ymax>649</ymax></bndbox></object><object><name>ship</name><pose>Unspecified</pose><truncated>0</truncated><difficult>0</difficult><bndbox><xmin>247</xmin><ymin>552</ymin><xmax>275</xmax><ymax>620</ymax></bndbox></object><object><name>ship</name><pose>Unspecified</pose><truncated>0</truncated><difficult>0</difficult><bndbox><xmin>363</xmin><ymin>586</ymin><xmax>382</xmax><ymax>652</ymax></bndbox></object><object><name>ship</name><pose>Unspecified</pose><truncated>0</truncated><difficult>0</difficult><bndbox><xmin>288</xmin><ymin>563</ymin><xmax>315</xmax><ymax>624</ymax></bndbox></object></annotation>